_version.py
pyopenlpt.cpython-312-x86_64-linux-gnu.so
openlpt.py
openlpt.libs/libgomp-24e2ab19.so.1.0.0
gui/style.qss
gui/test_pyqt.py
gui/create_shortcut.py
gui/main.py
gui/app.py
gui/__init__.py
gui/utils/update_checker.py
gui/utils/auto_updater.py
gui/utils/__init__.py
gui/assets/icon.png
gui/docs/index.html
gui/docs/results.html
gui/docs/tracking.html
gui/docs/settings.html
gui/docs/preprocessing.html
gui/docs/calibration/wand_guide.html
gui/docs/calibration/plate_guide.html
gui/docs/calibration/wand_detection_ui.png
gui/docs/calibration/plate_point_detection.png
gui/docs/calibration/wand_calibration_ui_v2.png
gui/docs/calibration/plate_calibration.png
gui/widgets/__init__.py
gui/views/tracking_settings_view.py
gui/views/camera_calibration_view.py
gui/views/results_view.py
gui/views/image_preprocessing_view.py
gui/views/tracking_view.py
gui/views/__init__.py
openlpt-2.1.8.dist-info/WHEEL
openlpt-2.1.8.dist-info/entry_points.txt
openlpt-2.1.8.dist-info/top_level.txt
openlpt-2.1.8.dist-info/METADATA
openlpt-2.1.8.dist-info/RECORD
openlpt-2.1.8.dist-info/licenses/LICENSE
modules/__init__.py
modules/image_preprocessing/widgets.py
modules/image_preprocessing/__init__.py
modules/image_preprocessing/view.py
modules/post_processing/processor.py
modules/post_processing/__init__.py
modules/vsc/camera_io.py
modules/vsc/optimizer.py
modules/vsc/vsc_service.py
modules/vsc/__init__.py
modules/camera_calibration/widgets.py
modules/camera_calibration/__init__.py
modules/camera_calibration/view.py
modules/camera_calibration/plate_calibration/PLATE_CALIBRATION_USER_GUIDE.html
modules/camera_calibration/plate_calibration/plate_point_detection.png
modules/camera_calibration/plate_calibration/grid_detector.py
modules/camera_calibration/plate_calibration/plate_calibration.png
modules/camera_calibration/wand_calibration/update_guide_v2.py
modules/camera_calibration/wand_calibration/wand_calibrator.py
modules/camera_calibration/wand_calibration/wand_detection_ui.png
modules/camera_calibration/wand_calibration/wand_calibration_ui.png
modules/camera_calibration/wand_calibration/wand_calibration_ui_v2.png
