Metadata-Version: 2.4
Name: openlpt
Version: 2.1.8
Summary: Open-source Lagrangian Particle Tracking (LPT) with GUI and CLI
Author-email: "Shiyong Tan @ JHU Ni Research Lab" <tanshiyong84@gmail.com>
License: MIT
Project-URL: Homepage, https://github.com/Sinchy/pyOpenLPT
Classifier: Programming Language :: Python :: 3
Classifier: Programming Language :: C++
Classifier: Operating System :: OS Independent
Classifier: Topic :: Scientific/Engineering :: Physics
Classifier: Topic :: Scientific/Engineering :: Visualization
Requires-Python: >=3.10
License-File: LICENSE
Requires-Dist: numpy>=2.2.0
Requires-Dist: pandas>=2.2.2
Requires-Dist: pybind11>=2.10
Requires-Dist: scipy>=1.11.0
Requires-Dist: opencv-python>=4.8.0
Requires-Dist: scikit-learn>=1.0.0
Requires-Dist: numba>=0.60.0
Requires-Dist: matplotlib>=3.7.0
Requires-Dist: requests>=2.31.0
Requires-Dist: pycine>=0.3.2
Requires-Dist: pywin32>=306; sys_platform == "win32"
Provides-Extra: gui
Requires-Dist: PySide6>=6.6.0; extra == "gui"
Requires-Dist: qtawesome>=1.3.0; extra == "gui"
Dynamic: license-file
